anidb/__init__.py
anidb/compat.py
anidb/helper.py
anidb/models.py
anidb/searchModels.py
anidb/urls.py
anidouga_anidb.py-1.0.1.dev44.dist-info/METADATA
anidouga_anidb.py-1.0.1.dev44.dist-info/RECORD
anidouga_anidb.py-1.0.1.dev44.dist-info/WHEEL
anidouga_anidb.py-1.0.1.dev44.dist-info/pbr.json
anidouga_anidb.py-1.0.1.dev44.dist-info/top_level.txt
