Metadata-Version: 2.1
Name: anidouga-anidb.py
Version: 1.0.1.dev44
Summary: Python interface for the AniDB HTTP API
Home-page: https://git.widmer.me/root/anidb.py
Author: Joel Widmer
Author-email: joel.widmer.wj@gmail.com
License: UNKNOWN
Platform: UNKNOWN
Classifier: Intended Audience :: Developers
Classifier: License :: OSI Approved :: Apache Software License
Classifier: Operating System :: OS Independent
Classifier: Programming Language :: Python
Classifier: Programming Language :: Python :: 3.6
Classifier: Topic :: Software Development :: Libraries
Requires-Dist: appdirs
Requires-Dist: requests
Requires-Dist: requests-cache
Requires-Dist: fuzzywuzzy
